pycrdt/websocket/__init__.py
pycrdt/websocket/asgi_server.py
pycrdt/websocket/awareness.py
pycrdt/websocket/django_channels_consumer.py
pycrdt/websocket/py.typed
pycrdt/websocket/websocket.py
pycrdt/websocket/websocket_server.py
pycrdt/websocket/yroom.py
pycrdt/websocket/yutils.py
pycrdt_websocket-0.16.0.dist-info/METADATA
pycrdt_websocket-0.16.0.dist-info/WHEEL
pycrdt_websocket-0.16.0.dist-info/licenses/LICENSE
pycrdt_websocket-0.16.0.dist-info/RECORD
