Metadata-Version: 2.4
Name: pycrdt-websocket
Version: 0.16.0
Summary: WebSocket connector for pycrdt
Project-URL: Homepage, https://github.com/y-crdt/pycrdt-websocket
Project-URL: Source, https://github.com/y-crdt/pycrdt-websocket
Project-URL: Issues, https://github.com/y-crdt/pycrdt-websocket/issues
Project-URL: Pypi, https://pypi.org/project/pycrdt-websocket
Author-email: David Brochart <david.brochart@gmail.com>
License: MIT License
License-File: LICENSE
Keywords: websocket,yjs
Classifier: Development Status :: 4 - Beta
Classifier: Intended Audience :: Developers
Classifier: License :: OSI Approved :: MIT License
Classifier: Programming Language :: Python
Classifier: Programming Language :: Python :: 3.9
Classifier: Programming Language :: Python :: 3.10
Classifier: Programming Language :: Python :: 3.11
Classifier: Programming Language :: Python :: 3.12
Classifier: Programming Language :: Python :: 3.13
Requires-Python: >=3.9
Requires-Dist: anyio<5,>=3.6.2
Requires-Dist: pycrdt-store<0.2.0,>=0.1.0
Requires-Dist: pycrdt<0.13.0,>=0.12.16
Provides-Extra: django
Requires-Dist: channels; extra == 'django'
